hsc_to_lci/__init__.py
hsc_to_lci/converter.py
hsc_to_lci/utils.py
hsc_to_lci-0.0.2.dist-info/LICENSE
hsc_to_lci-0.0.2.dist-info/METADATA
hsc_to_lci-0.0.2.dist-info/WHEEL
hsc_to_lci-0.0.2.dist-info/top_level.txt
hsc_to_lci-0.0.2.dist-info/RECORD
