Metadata-Version: 2.1
Name: hsc-to-lci
Version: 0.0.2
Summary: Convert HSC Chemistry simulation results to Brightway-format life cycle inventories
Home-page: https://github.com/robyistrate/hsc_to_lci
Author: Robert Istrate <i.r.istrate@cml.leidenuniv.nl>
License: BSD 3-Clause License
Classifier: Intended Audience :: Science/Research
Classifier: Programming Language :: Python
Classifier: Programming Language :: Python :: 3
Classifier: Programming Language :: Python :: 3.9
Classifier: License :: OSI Approved :: BSD License
Classifier: Operating System :: MacOS :: MacOS X
Classifier: Operating System :: Microsoft :: Windows
Classifier: Operating System :: POSIX
Requires-Python: >=3.9,<3.12
License-File: LICENSE
Requires-Dist: brightway2
